achoz/__init__.py
achoz/central_controller.py
achoz/cli.py
achoz/config.py
achoz/crawler.py
achoz/extension_pattern_modi.py
achoz/file_lister.py
achoz/get_obj_size.py
achoz/global_var.py
achoz/index_mngr.py
achoz/list_write.py
achoz/meili_installer.py
achoz/server.py
achoz/text_cleaner.py
achoz/text_extractor.py
achoz/unique_id_generator.py
achoz/static/css/app.css
achoz/static/html/index.html
achoz/static/html/search.html
achoz/static/html/video.html
achoz/static/img/achoz.png
achoz/static/js/search.js
achoz-0.3.65.dist-info/LICENSE
achoz-0.3.65.dist-info/METADATA
achoz-0.3.65.dist-info/WHEEL
achoz-0.3.65.dist-info/entry_points.txt
achoz-0.3.65.dist-info/top_level.txt
achoz-0.3.65.dist-info/RECORD
