Metadata-Version: 2.1
Name: achoz
Version: 0.3.65
Summary: Search through all your documents like web
Author: Krishna Kanhaiya < kcubeterm >
Author-email: kcubeterm@gmail.com
License: AGPL-3
Classifier: Environment :: Console
Classifier: Environment :: Web Environment
Classifier: Development Status :: 4 - Beta
Classifier: Intended Audience :: End Users/Desktop
Classifier: Intended Audience :: Developers
Classifier: Intended Audience :: Education
Classifier: Intended Audience :: Information Technology
Classifier: Intended Audience :: System Administrators
Classifier: License :: OSI Approved :: GNU Affero General Public License v3 or later (AGPLv3+)
Classifier: Operating System :: Unix
Classifier: Operating System :: POSIX :: Linux
Classifier: Topic :: Text Processing
Classifier: Topic :: Text Processing :: Indexing
Requires-Python: >=3.8
License-File: LICENSE
Requires-Dist: meilisearch (>=0.18.3)
Requires-Dist: pyramid (>=2.0)
Requires-Dist: pyinotify (>=0.9.6)
Requires-Dist: requests (>=2.22.0)
Requires-Dist: schedule (>=1.1.0)
Requires-Dist: textract (>=1.6.5)
